lyrix_api/__init__.py
lyrix_api/api.py
lyrix_api/meta.py
lyrix_api-0.1.3.dist-info/WHEEL
lyrix_api-0.1.3.dist-info/METADATA
lyrix_api-0.1.3.dist-info/RECORD
