Metadata-Version: 2.1
Name: lyrix-api
Version: 0.1.3
Summary: Python bindings for Lyrix backend
License: MIT
Author: Srevin Saju
Author-email: srevinsaju@sugarlabs.org
Requires-Python: >=3.6,<4.0
Classifier: License :: OSI Approved :: MIT License
Classifier: Programming Language :: Python :: 3
Classifier: Programming Language :: Python :: 3.6
Classifier: Programming Language :: Python :: 3.7
Classifier: Programming Language :: Python :: 3.8
Classifier: Programming Language :: Python :: 3.9
Requires-Dist: requests (>=2.25.1,<3.0.0)
